biolexica/.DS_Store
biolexica/__init__.py
biolexica/__main__.py
biolexica/api.py
biolexica/cli.py
biolexica/configs/__init__.py
biolexica/configs/anatomy.py
biolexica/configs/cell.py
biolexica/configs/phenotype.py
biolexica/py.typed
biolexica/version.py
biolexica-0.1.0.dist-info/licenses/LICENSE
biolexica-0.1.0.dist-info/WHEEL
biolexica-0.1.0.dist-info/entry_points.txt
biolexica-0.1.0.dist-info/METADATA
biolexica-0.1.0.dist-info/RECORD
