Metadata-Version: 2.4
Name: biolexica
Version: 0.1.0
Summary: Generate and apply coherent biomedical lexical indices for NER and NEN
Keywords: snekpack,cookiecutter,biomedicine,chemistry,named entity recognition,named entity normalization,natural language processing,NLP,NER,NEN
Author: Charles Tapley Hoyt
Author-email: Charles Tapley Hoyt <cthoyt@gmail.com>
License-File: LICENSE
Classifier: Development Status :: 1 - Planning
Classifier: Environment :: Console
Classifier: Intended Audience :: Developers
Classifier: License :: OSI Approved :: MIT License
Classifier: Operating System :: OS Independent
Classifier: Framework :: Pytest
Classifier: Framework :: tox
Classifier: Framework :: Sphinx
Classifier: Natural Language :: English
Classifier: Programming Language :: Python
Classifier: Programming Language :: Python :: 3.10
Classifier: Programming Language :: Python :: 3.11
Classifier: Programming Language :: Python :: 3.12
Classifier: Programming Language :: Python :: 3.13
Classifier: Programming Language :: Python :: 3 :: Only
Classifier: Typing :: Typed
Requires-Dist: semra
Requires-Dist: ssslm>=0.0.10
Requires-Dist: bioregistry
Requires-Dist: pyobo
Requires-Dist: bioontologies>=0.6.0
Requires-Dist: biosynonyms
Requires-Dist: pandas
Requires-Dist: tqdm
Requires-Dist: click
Requires-Dist: biomappings
Requires-Dist: sphinx>=8 ; extra == 'docs'
Requires-Dist: sphinx-rtd-theme>=3.0 ; extra == 'docs'
Requires-Dist: sphinx-click ; extra == 'docs'
Requires-Dist: sphinx-automodapi ; extra == 'docs'
Requires-Dist: autodoc-pydantic ; extra == 'docs'
Requires-Dist: ssslm[gilda] ; extra == 'gilda'
Requires-Dist: ssslm[gilda-slim] ; extra == 'gilda-slim'
Requires-Dist: pytest ; extra == 'tests'
Requires-Dist: coverage[toml] ; extra == 'tests'
Maintainer: Charles Tapley Hoyt
Maintainer-email: Charles Tapley Hoyt <cthoyt@gmail.com>
Requires-Python: >=3.10
Project-URL: Bug Tracker, https://github.com/biopragmatics/biolexica/issues
Project-URL: Documentation, https://biolexica.readthedocs.io
Project-URL: Funding, https://github.com/sponsors/cthoyt
Project-URL: Homepage, https://github.com/biopragmatics/biolexica
Project-URL: Repository, https://github.com/biopragmatics/biolexica.git
Provides-Extra: docs
Provides-Extra: gilda
Provides-Extra: gilda-slim
Provides-Extra: tests
